LICENSE
README.md
setup.py
pymediathek/__init__.py
pymediathek/const.py
pymediathek/model.py
pymediathek.egg-info/PKG-INFO
pymediathek.egg-info/SOURCES.txt
pymediathek.egg-info/dependency_links.txt
pymediathek.egg-info/requires.txt
pymediathek.egg-info/top_level.txt
pymediathek.egg-info/zip-safe